entegywrapper/__init__.py
entegywrapper/attendance_tracking/__init__.py
entegywrapper/attendance_tracking/attendance_tracking.py
entegywrapper/content/__init__.py
entegywrapper/content/categories.py
entegywrapper/content/content.py
entegywrapper/content/documents.py
entegywrapper/content/multi_link.py
entegywrapper/errors.py
entegywrapper/notification/__init__.py
entegywrapper/notification/notification.py
entegywrapper/plugins/__init__.py
entegywrapper/plugins/ext_auth.py
entegywrapper/points/__init__.py
entegywrapper/points/point_management.py
entegywrapper/profiles/__init__.py
entegywrapper/profiles/profile_custom.py
entegywrapper/profiles/profile_links.py
entegywrapper/profiles/profile_payments.py
entegywrapper/profiles/profile_types.py
entegywrapper/profiles/profiles.py
entegywrapper/py.typed
entegywrapper/schemas/__init__.py
entegywrapper/schemas/attendance_tracking.py
entegywrapper/schemas/content.py
entegywrapper/schemas/lead_capture.py
entegywrapper/schemas/page_settings.py
entegywrapper/schemas/points.py
entegywrapper/schemas/profile.py
entegywrapper/schemas/project.py
entegywrapper/schemas/schedule.py
entegywrapper-9.0.4.dist-info/METADATA
entegywrapper-9.0.4.dist-info/WHEEL
entegywrapper-9.0.4.dist-info/RECORD
