Metadata-Version: 2.1
Name: entegywrapper
Version: 9.0.4
Summary: Python SDK for the Entegy API
Home-page: https://github.com/SituDevelopment/entegy-sdk-python
Author: Situ Development
Author-email: developer@situ.com.au
Requires-Python: >=3.10.0,<4.0.0
Classifier: License :: OSI Approved :: BSD License
Classifier: Programming Language :: Python :: 3
Classifier: Programming Language :: Python :: 3.10
Classifier: Programming Language :: Python :: 3.11
Classifier: Programming Language :: Python :: 3.12
Requires-Dist: pydantic (>=2.6.0,<3.0.0)
Requires-Dist: requests (>=2.31,<2.33)
Project-URL: Repository, https://github.com/SituDevelopment/entegy-sdk-python
